{
  "required": true,
  "package": "me.deftware.mixin.mixins",
  "compatibilityLevel": "JAVA_8",
  "refmap": "mixins.emc.refmap.json",
  "mixins": [
    "MixinAbstractClientPlayer",
    "MixinAbstractHorse",
    "MixinAbstractPig",
    "MixinBlock",
    "MixinBlockCactus",
    "MixinBlockFluidRenderer",
    "MixinBlockModelRenderer",
    "MixinBlockSoulSand",
    "MixinBlockState",
    "MixinChatSuggestion",
    "MixinClientBrandRetriever",
    "MixinCPacketPlayer",
    "MixinEnderEyeEntity",
    "MixinEntity",
    "MixinEntityLivingBase",
    "MixinEntityPlayerSP",
    "MixinEntityRenderer",
    "MixinFilledMapItem",
    "MixinGlStateManager",
    "MixinGuiButton",
    "MixinGuiChat",
    "MixinGuiConnecting",
    "MixinGuiContainer",
    "MixinGuiDisconnected",
    "MixinGuiEditSign",
    "MixinGuiGameOver",
    "MixinGuiIngame",
    "MixinGuiMainMenu",
    "MixinGuiNewChat",
    "MixinGuiScreen",
    "MixinGuiTextField",
    "MixinInGameOverlayRenderer",
    "MixinItemStack",
    "MixinItemTool",
    "MixinKeyBinding",
    "MixinKeyboardListener",
    "MixinLayerDeadmau5Head",
    "MixinMinecraft",
    "MixinMouseHelper",
    "MixinMovementInputFromOptions",
    "MixinNetHandlerLoginClient",
    "MixinNetHandlerPlayClient",
    "MixinNetworkManager",
    "MixinNetworkPlayerInfo",
    "MixinPlayerControllerMP",
    "MixinPlayerEntity",
    "MixinPlayerListEntry",
    "MixinRender",
    "MixinRenderLivingBase",
    "MixinRenderManager",
    "MixinRenderPlayer",
    "MixinRenderSystem",
    "MixinServerListEntryNormal",
    "MixinSkinManager",
    "MixinSplashScreen",
    "MixinSweetBerryBushBlock",
    "MixinTextRenderer",
    "MixinTextureManager",
    "MixinTimer",
    "MixinVisGraph",
    "MixinWorldClient",
    "MixinWorldRenderer"
  ]
}
